{
  "id": "kali:libtext-xslate-perl",
  "kind": "kali_source_package",
  "name": "libtext-xslate-perl",
  "title": "libtext-xslate-perl",
  "summary": "scalable template engine for Perl 5 (C/XS accelerated)",
  "description": "scalable template engine for Perl 5 (C/XS accelerated)\nText::Xslate is a template engine, tuned for persistent applications, safe\nas an HTML generator, and with rich features.\n.\nThere are a lot of template engines in CPAN, for example Template-Toolkit,\nText::MicroTemplate, HTML::Template, and so on, but all of them have some\nweak points: a full-featured template engine may be slow, while a fast\ntemplate engine may be too simple to use. This is why Text::Xslate is\ndeveloped, which is to be the best template engine for web applications.\n.\nThe concept of Text::Xslate is strongly influenced by Text::MicroTemplate and\nTemplate-Toolkit 2, but the central philosophy of Text::Xslate is different\nfrom them. That is, the philosophy is one of sandboxing; that the template\nlogic should not have no access outside the template beyond your permission.",
  "version": "3.5.9-2+b2",
  "architectures": [
    "amd64"
  ],
  "homepage": "https://metacpan.org/release/Text-Xslate",
  "repository": "https://metacpan.org/release/Text-Xslate",
  "source_package": "libtext-xslate-perl (3.5.9-2)",
  "metapackages": [],
  "install": {
    "apt": "sudo apt install libtext-xslate-perl"
  },
  "packages": [
    {
      "name": "libtext-xslate-perl"
    }
  ],
  "commands": [
    {
      "name": "xslate",
      "path": "/usr/bin/xslate",
      "description": "Process Xslate Templates",
      "usage": "xslate [options] [args]",
      "arguments": []
    }
  ],
  "files": [
    "/usr/bin/xslate",
    "/usr/share/man/man1/xslate.1p.gz",
    "/usr/share/man/man3/Text::Xslate.3pm.gz",
    "/usr/share/man/man3/Text::Xslate::Bridge.3pm.gz",
    "/usr/share/man/man3/Text::Xslate::Bridge::Star.3pm.gz",
    "/usr/share/man/man3/Text::Xslate::Compiler.3pm.gz",
    "/usr/share/man/man3/Text::Xslate::HashWithDefault.3pm.gz",
    "/usr/share/man/man3/Text::Xslate::Manual.3pm.gz",
    "/usr/share/man/man3/Text::Xslate::Manual::Builtin.3pm.gz",
    "/usr/share/man/man3/Text::Xslate::Manual::Cookbook.3pm.gz",
    "/usr/share/man/man3/Text::Xslate::Manual::Debugging.3pm.gz",
    "/usr/share/man/man3/Text::Xslate::Manual::FAQ.3pm.gz",
    "/usr/share/man/man3/Text::Xslate::PP.3pm.gz",
    "/usr/share/man/man3/Text::Xslate::PP::Const.3pm.gz",
    "/usr/share/man/man3/Text::Xslate::PP::Method.3pm.gz",
    "/usr/share/man/man3/Text::Xslate::PP::Opcode.3pm.gz",
    "/usr/share/man/man3/Text::Xslate::PP::State.3pm.gz",
    "/usr/share/man/man3/Text::Xslate::PP::Type::Macro.3pm.gz",
    "/usr/share/man/man3/Text::Xslate::PP::Type::Pair.3pm.gz",
    "/usr/share/man/man3/Text::Xslate::PP::Type::Raw.3pm.gz",
    "/usr/share/man/man3/Text::Xslate::Parser.3pm.gz",
    "/usr/share/man/man3/Text::Xslate::Runner.3pm.gz",
    "/usr/share/man/man3/Text::Xslate::Symbol.3pm.gz",
    "/usr/share/man/man3/Text::Xslate::Syntax::Kolon.3pm.gz",
    "/usr/share/man/man3/Text::Xslate::Syntax::Metakolon.3pm.gz",
    "/usr/share/man/man3/Text::Xslate::Syntax::TTerse.3pm.gz",
    "/usr/share/man/man3/Text::Xslate::Type::Raw.3pm.gz",
    "/usr/share/man/man3/Text::Xslate::Util.3pm.gz"
  ],
  "tags": [
    "os-package",
    "library"
  ],
  "metadata_status": "os_generated",
  "schema_version": "1.1.0",
  "attack_surface": "local",
  "phase_hint": "install",
  "requires_hardware": false
}