{
  "id": "kali:python3-rarfile",
  "kind": "kali_source_package",
  "name": "python3-rarfile",
  "title": "python3-rarfile",
  "summary": "RAR archive reader module for Python",
  "description": "RAR archive reader module for Python\nRarfile is a Python module for reading RAR archives. The interface is made\nas zipfile-like as possible. It supports both RAR3 and RAR5 archives,\nmulti volumes archives, unicode filenames and password-protected archives.",
  "version": "4.3-1",
  "architectures": [
    "all"
  ],
  "homepage": "https://github.com/markokr/rarfile",
  "repository": "https://github.com/markokr/rarfile",
  "source_package": "python-rarfile",
  "metapackages": [],
  "install": {
    "apt": "sudo apt install python3-rarfile"
  },
  "packages": [
    {
      "name": "python3-rarfile"
    }
  ],
  "commands": [],
  "files": [],
  "tags": [
    "os-package",
    "python"
  ],
  "metadata_status": "os_generated",
  "schema_version": "1.1.0",
  "attack_surface": "local",
  "phase_hint": "install",
  "requires_hardware": false
}