{
  "id": "kali:python3-flatbuffers",
  "kind": "kali_source_package",
  "name": "python3-flatbuffers",
  "title": "python3-flatbuffers",
  "summary": "efficient cross platform serialization library - Python bindings",
  "description": "efficient cross platform serialization library - Python bindings\nFlatBuffers is an efficient cross platform serialization library for C++, C#,\nC, Go, Java, JavaScript, TypeScript, PHP, and Python. It was originally\ncreated at Google for game development and other performance-critical\napplications.\n.\nThis package contains python3 flatbuffers API.",
  "version": "23.5.26+dfsg-4",
  "architectures": [
    "all"
  ],
  "homepage": "https://google.github.io/flatbuffers/",
  "repository": "https://google.github.io/flatbuffers/",
  "source_package": "flatbuffers",
  "metapackages": [],
  "install": {
    "apt": "sudo apt install python3-flatbuffers"
  },
  "packages": [
    {
      "name": "python3-flatbuffers"
    }
  ],
  "commands": [],
  "files": [],
  "tags": [
    "os-package",
    "python"
  ],
  "metadata_status": "os_generated",
  "schema_version": "1.1.0",
  "attack_surface": "local",
  "phase_hint": "install",
  "requires_hardware": false
}