{
  "id": "kali:soapysdr0.8-module-audio",
  "kind": "kali_source_package",
  "name": "soapysdr0.8-module-audio",
  "title": "soapysdr0.8-module-audio",
  "summary": "Audio device support for SoapySDR",
  "description": "Audio device support for SoapySDR\nThe SoapyAudio project provides a SoapySDR module for using Software\nDefined Radio devices that are connected through audio interfaces.\nIt uses hamlib to provide control of tuning and other functions where\navailable.",
  "version": "0.1.1-7+b1",
  "architectures": [
    "amd64"
  ],
  "homepage": "https://github.com/pothosware/SoapyAudio/wiki",
  "repository": "https://github.com/pothosware/SoapyAudio/wiki",
  "source_package": "soapyaudio (0.1.1-7)",
  "metapackages": [],
  "install": {
    "apt": "sudo apt install soapysdr0.8-module-audio"
  },
  "packages": [
    {
      "name": "soapysdr0.8-module-audio"
    }
  ],
  "commands": [],
  "files": [],
  "tags": [
    "os-package"
  ],
  "metadata_status": "os_generated",
  "schema_version": "1.1.0",
  "attack_surface": "local",
  "phase_hint": "install",
  "requires_hardware": false
}