{
  "id": "kali:node-eslint-utils",
  "kind": "kali_source_package",
  "name": "node-eslint-utils",
  "title": "node-eslint-utils",
  "summary": "utilities for ESLint plugins",
  "description": "utilities for ESLint plugins\neslint-utils provides utility functions and classes\nfor making ESLint custom rules.\n.\nESLint is a tool for identifying and reporting on patterns\nfound in ECMAScript/JavaScript code.\n.\nNode.js is an event-based server-side JavaScript engine.",
  "version": "3.0.0-4",
  "architectures": [
    "all"
  ],
  "homepage": "https://github.com/mysticatea/eslint-utils",
  "repository": "https://github.com/mysticatea/eslint-utils",
  "source_package": "node-eslint-utils",
  "metapackages": [],
  "install": {
    "apt": "sudo apt install node-eslint-utils"
  },
  "packages": [
    {
      "name": "node-eslint-utils"
    }
  ],
  "commands": [],
  "files": [],
  "tags": [
    "os-package"
  ],
  "metadata_status": "os_generated",
  "schema_version": "1.1.0",
  "attack_surface": "local",
  "phase_hint": "install",
  "requires_hardware": false
}