{
  "id": "kali:node-gauge",
  "kind": "kali_source_package",
  "name": "node-gauge",
  "title": "node-gauge",
  "summary": "terminal based horizontal progress bar",
  "description": "terminal based horizontal progress bar\nA nearly stateless terminal based horizontal gauge / progress bar.  This\nlibrary is a dependency for npmlog, a logger with custom levels and colored\noutput for Node.js\n.\nNode.js is an event-based server-side JavaScript engine.",
  "version": "4.0.4-2",
  "architectures": [
    "all"
  ],
  "homepage": "https://github.com/npm/gauge",
  "repository": "https://github.com/npm/gauge",
  "source_package": "node-gauge",
  "metapackages": [],
  "install": {
    "apt": "sudo apt install node-gauge"
  },
  "packages": [
    {
      "name": "node-gauge"
    }
  ],
  "commands": [],
  "files": [],
  "tags": [
    "os-package"
  ],
  "metadata_status": "os_generated",
  "schema_version": "1.1.0",
  "attack_surface": "local",
  "phase_hint": "install",
  "requires_hardware": false
}