{
  "id": "kali:wgetpaste",
  "kind": "kali_source_package",
  "name": "wgetpaste",
  "title": "wgetpaste",
  "summary": "### wgetpaste",
  "version": "2.30-0kali1",
  "architectures": [
    "all"
  ],
  "homepage": "http://wgetpaste.zlin.dk/",
  "repository": "https://gitlab.com/kalilinux/packages/wgetpaste",
  "metapackages": [
    "kali-linux-everything"
  ],
  "install": {
    "apt": "sudo apt install wgetpaste"
  },
  "packages": [
    {
      "name": "wgetpaste"
    }
  ],
  "commands": [
    {
      "name": "wgetpaste",
      "description": "- - -",
      "usage": "/usr/bin/wgetpaste [options] [file[s]]",
      "arguments": [
        {
          "flags": [
            "-l",
            "--language"
          ],
          "metavar": "- anguage LANG",
          "takes_value": true,
          "description": "set language (defaults to \"Plain Text\")",
          "default": "s to \"Plain Text\"",
          "choices": null,
          "raw": "   -l, --language LANG           set language (defaults to \"Plain Text\")"
        },
        {
          "flags": [
            "-d",
            "--description"
          ],
          "metavar": "- escription DESCRIPTION set description defaults to \"stdin\" or filename",
          "takes_value": true,
          "description": "",
          "default": null,
          "choices": null,
          "raw": "   -d, --description DESCRIPTION set description (defaults to \"stdin\" or filename)"
        },
        {
          "flags": [
            "-n",
            "--nick"
          ],
          "metavar": "- ick NICK",
          "takes_value": true,
          "description": "set nick (defaults to your username)",
          "default": "s to your username",
          "choices": null,
          "raw": "   -n, --nick NICK               set nick (defaults to your username)"
        },
        {
          "flags": [
            "-s",
            "--service"
          ],
          "metavar": "- ervice SERVICE",
          "takes_value": true,
          "description": "set service to use (defaults to \"dpaste\")",
          "default": "s to \"dpaste\"",
          "choices": null,
          "raw": "   -s, --service SERVICE         set service to use (defaults to \"dpaste\")"
        },
        {
          "flags": [
            "-e",
            "--expiration"
          ],
          "metavar": "- xpiration EXPIRATION",
          "takes_value": true,
          "description": "set when it should expire (defaults to \"30 days\")",
          "default": "s to \"30 days\"",
          "choices": null,
          "raw": "   -e, --expiration EXPIRATION   set when it should expire (defaults to \"30 days\")"
        },
        {
          "flags": [
            "-S",
            "--list-services"
          ],
          "metavar": null,
          "takes_value": false,
          "description": "list supported pastebin services",
          "default": null,
          "choices": null,
          "raw": "   -S, --list-services           list supported pastebin services"
        },
        {
          "flags": [
            "-L",
            "--list-languages"
          ],
          "metavar": null,
          "takes_value": false,
          "description": "list languages supported by the specified service",
          "default": null,
          "choices": null,
          "raw": "   -L, --list-languages          list languages supported by the specified service"
        },
        {
          "flags": [
            "-E",
            "--list-expiration"
          ],
          "metavar": null,
          "takes_value": false,
          "description": "list expiration setting supported by the specified service",
          "default": null,
          "choices": null,
          "raw": "   -E, --list-expiration         list expiration setting supported by the specified service"
        },
        {
          "flags": [
            "-u",
            "--tinyurl"
          ],
          "metavar": "URL",
          "takes_value": true,
          "description": "convert input url to tinyurl",
          "default": null,
          "choices": null,
          "raw": "   -u, --tinyurl URL             convert input url to tinyurl"
        },
        {
          "flags": [
            "-c",
            "--command"
          ],
          "metavar": "- ommand COMMAND",
          "takes_value": true,
          "description": "paste COMMAND and the output of COMMAND",
          "default": null,
          "choices": null,
          "raw": "   -c, --command COMMAND         paste COMMAND and the output of COMMAND"
        },
        {
          "flags": [
            "-i",
            "--info"
          ],
          "metavar": "- nfo",
          "takes_value": true,
          "description": "append the output of `emerge --info`",
          "default": null,
          "choices": null,
          "raw": "   -i, --info                    append the output of `emerge --info`"
        },
        {
          "flags": [
            "-I",
            "--info-only"
          ],
          "metavar": null,
          "takes_value": false,
          "description": "paste the output of `emerge --info` only",
          "default": null,
          "choices": null,
          "raw": "   -I, --info-only               paste the output of `emerge --info` only"
        },
        {
          "flags": [
            "-x",
            "--xcut"
          ],
          "metavar": "- cut",
          "takes_value": true,
          "description": "read input from clipboard (requires x11-misc/xclip)",
          "default": null,
          "choices": null,
          "raw": "   -x, --xcut                    read input from clipboard (requires x11-misc/xclip)"
        },
        {
          "flags": [
            "-X",
            "--xpaste"
          ],
          "metavar": null,
          "takes_value": false,
          "description": "write resulting url to the X primary selection buffer (requires x11-misc/xclip)",
          "default": null,
          "choices": null,
          "raw": "   -X, --xpaste                  write resulting url to the X primary selection buffer (requires x11-misc/xclip)"
        },
        {
          "flags": [
            "-C",
            "--xclippaste"
          ],
          "metavar": null,
          "takes_value": false,
          "description": "write resulting url to the X clipboard selection buffer (requires x11-misc/xclip)",
          "default": null,
          "choices": null,
          "raw": "   -C, --xclippaste              write resulting url to the X clipboard selection buffer (requires x11-misc/xclip)"
        },
        {
          "flags": [
            "-r",
            "--raw"
          ],
          "metavar": "- aw",
          "takes_value": true,
          "description": "show url for the raw paste (no syntax highlighting or html)",
          "default": null,
          "choices": null,
          "raw": "   -r, --raw                     show url for the raw paste (no syntax highlighting or html)"
        },
        {
          "flags": [
            "-t",
            "--tee"
          ],
          "metavar": "- ee",
          "takes_value": true,
          "description": "use tee to show what is being pasted",
          "default": null,
          "choices": null,
          "raw": "   -t, --tee                     use tee to show what is being pasted"
        },
        {
          "flags": [
            "-v",
            "--verbose"
          ],
          "metavar": "- erbose",
          "takes_value": true,
          "description": "show wget stderr output if no url is received",
          "default": null,
          "choices": null,
          "raw": "   -v, --verbose                 show wget stderr output if no url is received"
        },
        {
          "flags": [
            "--completions"
          ],
          "metavar": null,
          "takes_value": false,
          "description": "emit output suitable for shell completions (only affects --list-*)",
          "default": null,
          "choices": null,
          "raw": "       --completions             emit output suitable for shell completions (only affects --list-*)"
        },
        {
          "flags": [
            "--debug"
          ],
          "metavar": null,
          "takes_value": false,
          "description": "be *very* verbose (implies -v)",
          "default": null,
          "choices": null,
          "raw": "       --debug                   be *very* verbose (implies -v)"
        },
        {
          "flags": [
            "-h",
            "--help"
          ],
          "metavar": "- elp",
          "takes_value": true,
          "description": "show this help",
          "default": null,
          "choices": null,
          "raw": "   -h, --help                    show this help"
        },
        {
          "flags": [
            "-g",
            "--ignore-configs"
          ],
          "metavar": null,
          "takes_value": false,
          "description": "ignore /etc/wgetpaste.conf, ~/.wgetpaste.conf etc.",
          "default": null,
          "choices": null,
          "raw": "   -g, --ignore-configs          ignore /etc/wgetpaste.conf, ~/.wgetpaste.conf etc."
        },
        {
          "flags": [
            "--version"
          ],
          "metavar": null,
          "takes_value": false,
          "description": "show version information",
          "default": null,
          "choices": null,
          "raw": "       --version                 show version information"
        }
      ],
      "raw_help": "root@kali:~# wgetpaste -h\n Usage: /usr/bin/wgetpaste [options] [file[s]]\n \n Options:\n   -l, --language LANG           set language (defaults to \"Plain Text\")\n   -d, --description DESCRIPTION set description (defaults to \"stdin\" or filename)\n   -n, --nick NICK               set nick (defaults to your username)\n   -s, --service SERVICE         set service to use (defaults to \"dpaste\")\n   -e, --expiration EXPIRATION   set when it should expire (defaults to \"30 days\")\n \n   -S, --list-services           list supported pastebin services\n   -L, --list-languages          list languages supported by the specified service\n   -E, --list-expiration         list expiration setting supported by the specified service\n \n   -u, --tinyurl URL             convert input url to tinyurl\n \n   -c, --command COMMAND         paste COMMAND and the output of COMMAND\n   -i, --info                    append the output of `emerge --info`\n   -I, --info-only               paste the output of `emerge --info` only\n   -x, --xcut                    read input from clipboard (requires x11-misc/xclip)\n   -X, --xpaste                  write resulting url to the X primary selection buffer (requires x11-misc/xclip)\n   -C, --xclippaste              write resulting url to the X clipboard selection buffer (requires x11-misc/xclip)\n \n   -r, --raw                     show url for the raw paste (no syntax highlighting or html)\n   -t, --tee                     use tee to show what is being pasted\n   -v, --verbose                 show wget stderr output if no url is received\n       --completions             emit output suitable for shell completions (only affects --list-*)\n       --debug                   be *very* verbose (implies -v)\n \n   -h, --help                    show this help\n   -g, --ignore-configs          ignore /etc/wgetpaste.conf, ~/.wgetpaste.conf etc.\n       --version                 show version information\n \n Defaults (DEFAULT_{NICK,LANGUAGE,EXPIRATION}[_${SERVICE}] and DEFAULT_SERVICE)\n can be overridden globally in /etc/wgetpaste.conf or /etc/wgetpaste.d/*.conf or\n per user in any of ~/.wgetpaste.conf or ~/.wgetpaste.d/*.conf.\n \n An additional http header can be passed by setting HEADER_${SERVICE} in any of the\n configuration files mentioned above. For example, authenticating with github gist:\n HEADER_gists=\"Authorization: token 1234abc56789...\", or with gitlab snippets:\n HEADER_snippets=\"PRIVATE-TOKEN: 1234abc56789...\"\n \n You can also set PUBLIC_gists='false' if you want to default to secret instead of\n public github gists. In the case of gitlab, you can set VISIBILITY_snippets= to\n 'public', 'private' or 'internal'\"\n \n To change your gitlab server, you can override the default API URL setting\n URL_snippets='https://gitlab.[server].com/api/v4/snippets'",
      "examples": [],
      "risk": {
        "level": "critical",
        "signals": [
          "rat"
        ],
        "requires_explicit_authorization": false,
        "allow_autonomous_execution": true,
        "examples_policy": "operational"
      },
      "local_help": {
        "--help": "Usage: /usr/bin/wgetpaste [options] [file[s]]\n\nOptions:\n    -l, --language LANG           set language (defaults to \"Plain Text\")\n    -d, --description DESCRIPTION set description (defaults to \"stdin\" or filename)\n    -n, --nick NICK               set nick (defaults to your username)\n    -s, --service SERVICE         set service to use (defaults to \"dpaste\")\n    -e, --expiration EXPIRATION   set when it should expire (defaults to \"30 days\")\n\n    -S, --list-services           list supported pastebin services\n    -L, --list-languages          list languages supported by the specified service\n    -E, --list-expiration         list expiration setting supported by the specified service\n\n    -u, --tinyurl URL             convert input url to tinyurl\n\n    -c, --command COMMAND         paste COMMAND and the output of COMMAND\n    -i, --info                    append the output of `emerge --info`\n    -I, --info-only               paste the output of `emerge --info` only\n    -x, --xcut                    read input from clipboard (requires x11-misc/xclip)\n    -X, --xpaste                  write resulting url to the X primary selection buffer (requires x11-misc/xclip)\n    -C, --xclippaste              write resulting url to the X clipboard selection buffer (requires x11-misc/xclip)\n\n    -r, --raw                     show url for the raw paste (no syntax highlighting or html)\n    -t, --tee                     use tee to show what is being pasted\n    -v, --verbose                 show wget stderr output if no url is received\n        --completions             emit output suitable for shell completions (only affects --list-*)\n        --debug                   be *very* verbose (implies -v)\n\n    -h, --help                    show this help\n    -g, --ignore-configs          ignore /etc/wgetpaste.conf, ~/.wgetpaste.conf etc.\n        --version                 show version information\n\nDefaults (DEFAULT_{NICK,LANGUAGE,EXPIRATION}[_${SERVICE}] and DEFAULT_SERVICE)\ncan be overridden globally in /etc/wgetpaste.conf or /etc/wgetpaste.d/*.conf or\nper user in any of ~/.wgetpaste.conf or ~/.wgetpaste.d/*.conf.\n\nAn additional http header can be passed by setting HEADER_${SERVICE} in any of the\nconfiguration files mentioned above. For example, authenticating with github gist:\nHEADER_gists=\"Authorization: token 1234abc56789...\", or with gitlab snippets:\nHEADER_snippets=\"PRIVATE-TOKEN: 1234abc56789...\"\n\nYou can also set PUBLIC_gists='false' if you want to default to secret instead of\npublic github gists. In the case of gitlab, you can set VISIBILITY_snippets= to\n'public', 'private' or 'internal'\"\n\nTo change your gitlab server, you can override the default API URL setting\nURL_snippets='https://gitlab.[server].com/api/v4/snippets'",
        "-h": "Usage: /usr/bin/wgetpaste [options] [file[s]]\n\nOptions:\n    -l, --language LANG           set language (defaults to \"Plain Text\")\n    -d, --description DESCRIPTION set description (defaults to \"stdin\" or filename)\n    -n, --nick NICK               set nick (defaults to your username)\n    -s, --service SERVICE         set service to use (defaults to \"dpaste\")\n    -e, --expiration EXPIRATION   set when it should expire (defaults to \"30 days\")\n\n    -S, --list-services           list supported pastebin services\n    -L, --list-languages          list languages supported by the specified service\n    -E, --list-expiration         list expiration setting supported by the specified service\n\n    -u, --tinyurl URL             convert input url to tinyurl\n\n    -c, --command COMMAND         paste COMMAND and the output of COMMAND\n    -i, --info                    append the output of `emerge --info`\n    -I, --info-only               paste the output of `emerge --info` only\n    -x, --xcut                    read input from clipboard (requires x11-misc/xclip)\n    -X, --xpaste                  write resulting url to the X primary selection buffer (requires x11-misc/xclip)\n    -C, --xclippaste              write resulting url to the X clipboard selection buffer (requires x11-misc/xclip)\n\n    -r, --raw                     show url for the raw paste (no syntax highlighting or html)\n    -t, --tee                     use tee to show what is being pasted\n    -v, --verbose                 show wget stderr output if no url is received\n        --completions             emit output suitable for shell completions (only affects --list-*)\n        --debug                   be *very* verbose (implies -v)\n\n    -h, --help                    show this help\n    -g, --ignore-configs          ignore /etc/wgetpaste.conf, ~/.wgetpaste.conf etc.\n        --version                 show version information\n\nDefaults (DEFAULT_{NICK,LANGUAGE,EXPIRATION}[_${SERVICE}] and DEFAULT_SERVICE)\ncan be overridden globally in /etc/wgetpaste.conf or /etc/wgetpaste.d/*.conf or\nper user in any of ~/.wgetpaste.conf or ~/.wgetpaste.d/*.conf.\n\nAn additional http header can be passed by setting HEADER_${SERVICE} in any of the\nconfiguration files mentioned above. For example, authenticating with github gist:\nHEADER_gists=\"Authorization: token 1234abc56789...\", or with gitlab snippets:\nHEADER_snippets=\"PRIVATE-TOKEN: 1234abc56789...\"\n\nYou can also set PUBLIC_gists='false' if you want to default to secret instead of\npublic github gists. In the case of gitlab, you can set VISIBILITY_snippets= to\n'public', 'private' or 'internal'\"\n\nTo change your gitlab server, you can override the default API URL setting\nURL_snippets='https://gitlab.[server].com/api/v4/snippets'",
        "help": "No input read. Nothing to paste. Aborting."
      },
      "binary_metadata": {
        "path": "/usr/bin/wgetpaste",
        "size_bytes": 34617,
        "is_symlink": false,
        "file_type": "Bourne-Again shell script, Unicode text, UTF-8 text executable"
      }
    }
  ],
  "risk": {
    "level": "critical",
    "signals": [
      "offensive_tool",
      "intrinsic",
      "remote_possible",
      "polymorphic_compatible",
      "target_adaptive_compatible"
    ],
    "requires_explicit_authorization": false,
    "allow_autonomous_execution": true,
    "examples_policy": "operational"
  },
  "source": {
    "official": true,
    "page": "https://www.kali.org/tools/wgetpaste/",
    "raw_markdown": "https://gitlab.com/kalilinux/documentation/kali-tools/-/raw/main/wgetpaste/index.md",
    "retrieved_at": "2026-07-14T13:09:01+00:00",
    "sha256": "f2069fa8b6d8f4ef65c13cd5fbdd213527f79c788c623a5590bbc999f155c694"
  },
  "apt_metadata": {
    "section": "misc",
    "installed_size": "49",
    "maintainer": "Kali Developers <devel@kali.org>",
    "architecture": "all",
    "version": "2.30-0kali1",
    "depends": "wget",
    "description": "Command-line interface to various online pastebin services\nThis package contains a script that automates pasting to a number of pastebin\nservices.",
    "homepage": "http://wgetpaste.zlin.dk/"
  },
  "tags": [
    "offensive",
    "wgetpaste",
    "web",
    "kfiosa",
    "indexed",
    "polymorphic",
    "target-adaptive"
  ],
  "use_cases": [
    "When you need Kali Linux, use wgetpaste because ### wgetpaste.",
    "When you need a concrete invocation, run `/usr/bin/wgetpaste [options] [file[s]]` as documented upstream for wgetpaste.",
    "When chaining Kali Linux tools, pair wgetpaste with sibling catalog entries sharing its attack_surface/phase_hint.",
    "When validating lab setup, run `wgetpaste --help` (or the README entrypoint) and confirm required hardware/deps from the catalog."
  ],
  "command_examples": [
    "/usr/bin/wgetpaste [options] [file[s]]"
  ],
  "attack_surface": [
    "web"
  ],
  "phase_hint": "any",
  "requires_hardware": [
    "none"
  ],
  "polymorphic_strategies": [
    "param_grammar"
  ],
  "target_adaptive_targets": [
    "target_class"
  ],
  "_kfiosa_enriched_schema": "1.1.0",
  "documentation": {
    "arguments": [],
    "examples": [
      "/usr/bin/wgetpaste [options] [file[s]]"
    ],
    "readme": "### wgetpaste",
    "how_to_use": "Install/setup: sudo apt install wgetpaste.",
    "when_to_use": "Use during the 'any' phase against surfaces [web] in the Kali Linux category. Fits when the engagement needs: ### wgetpaste.",
    "why_to_use": "Prefer this tool because: ### wgetpaste.",
    "usage_sections": [
      "Install with: sudo apt install wgetpaste"
    ]
  },
  "_kfiosa_enhanced_v3": true,
  "_enhanced_via": "offline"
}
