{
  "id": "kali:libemail-address-xs-perl",
  "kind": "kali_source_package",
  "name": "libemail-address-xs-perl",
  "title": "libemail-address-xs-perl",
  "summary": "Perl library for RFC 5322 address/group parsing and formatting",
  "description": "Perl library for RFC 5322 address/group parsing and formatting\nEmail::Address::XS implements RFC 5322 parser and formatter of email\naddresses and groups. It parses an input string from email headers which\ncontain a list of email addresses or a groups of email addresses (like From,\nTo, Cc, Bcc, Reply-To, Sender, ...). Also it can generate a string value for\nthose headers from a list of email addresses objects.\n.\nParser and formatter functionality is implemented in XS and uses shared code\nfrom Dovecot IMAP server.\n.\nIt is a drop-in replacement for the Email::Address module.",
  "version": "1.05-1+b4",
  "architectures": [
    "amd64"
  ],
  "homepage": "https://metacpan.org/release/Email-Address-XS",
  "repository": "https://metacpan.org/release/Email-Address-XS",
  "source_package": "libemail-address-xs-perl (1.05-1)",
  "metapackages": [],
  "install": {
    "apt": "sudo apt install libemail-address-xs-perl"
  },
  "packages": [
    {
      "name": "libemail-address-xs-perl"
    }
  ],
  "commands": [],
  "files": [
    "/usr/share/man/man3/Email::Address::XS.3pm.gz"
  ],
  "tags": [
    "os-package",
    "library"
  ],
  "metadata_status": "os_generated",
  "schema_version": "1.1.0",
  "attack_surface": "local",
  "phase_hint": "install",
  "requires_hardware": false
}